inkawuvp_pellet_dispenser/__init__.py
inkawuvp_pellet_dispenser/module.py
inkawuvp_pellet_dispenser-0.0.1.dist-info/METADATA
inkawuvp_pellet_dispenser-0.0.1.dist-info/WHEEL
inkawuvp_pellet_dispenser-0.0.1.dist-info/top_level.txt
inkawuvp_pellet_dispenser-0.0.1.dist-info/RECORD
