Metadata-Version: 2.1
Name: inkawuvp-pellet-dispenser
Version: 0.0.1
Summary: A Python package to contol IVP's pellet dispenser via USB
Author-email: Alexandre Tuleu <alexandre.tuleu.2005@polytechnique.org>
License: GNU General Public License v3 (GPLv3)
Project-URL: Homepage, https://github.com/iNkawuVervetProject/VerTIGo/tree/main/devices/pellet-dispenser/driver
Project-URL: Issues, https://github.com/iNkawuVervetProject/VerTIGo/issues?q=is%3Aissue+is%3Aopen+label%3A"pellet dispenser"
Project-URL: Repository, https://github.com/iNkawuVervetProject/VerTIGo
Keywords: pellet,dispenser,hardware,hid,Open Source Hardware
Classifier: License :: OSI Approved :: GNU General Public License v3 (GPLv3)
Classifier: Programming Language :: Python :: 3
Classifier: Programming Language :: Python :: 3 :: Only
Classifier: Programming Language :: Python :: 3.8
Classifier: Programming Language :: Python :: 3.9
Classifier: Programming Language :: Python :: 3.10
Classifier: Programming Language :: Python :: 3.11
Classifier: Programming Language :: Python :: Implementation :: CPython
Classifier: License :: OSI Approved :: MIT License
Classifier: Operating System :: OS Independent
Requires-Python: >=3.8
Requires-Dist: hid
